webappalyzer/Wappalyzer.py
webappalyzer/__init__.py
webappalyzer/__main__.py
webappalyzer/fingerprint.py
webappalyzer/data/technologies.json
webappalyzer/webpage/__init__.py
webappalyzer/webpage/_bs4.py
webappalyzer/webpage/_common.py
webappalyzer/webpage/_stdlib.py
python3_webappalyzer-1.1.1.dist-info/LICENSE
python3_webappalyzer-1.1.1.dist-info/METADATA
python3_webappalyzer-1.1.1.dist-info/WHEEL
python3_webappalyzer-1.1.1.dist-info/top_level.txt
python3_webappalyzer-1.1.1.dist-info/RECORD
