Metadata-Version: 2.1
Name: python3-webappalyzer
Version: 1.1.1
Summary: Python implementation of the Wappalyzer web application detection utility.
Home-page: https://github.com/nmmapper/wappalyzer
Author: nmmapper
Author-email: info@nmmapper.com
License: UNKNOWN
Project-URL: Documentation, https://github.com/nmmapper/wappalyzer
Project-URL: How it is used, https://www.nmmapper.com/sys/cms-detection/wappalyzer-online/
Project-URL: Homepage, https://github.com/nmmapper/wappalyzer
Project-URL: Source, https://github.com/nmmapper/wappalyzer
Platform: UNKNOWN
Classifier: Programming Language :: Python :: 3
Classifier: Operating System :: OS Independent
Requires-Python: >=3.6
License-File: LICENSE
Requires-Dist: aiohttp
Requires-Dist: beautifulsoup4
Requires-Dist: cached-property
Requires-Dist: dom-query
Requires-Dist: lxml
Requires-Dist: requests
